maleo/toolkit/text/__init__.py
maleo/toolkit/text/code.py
maleo/toolkit/text/enums.py
maleo/toolkit/text/extractor.py
maleo/toolkit/text/loader.py
maleo_toolkit_text-0.0.5.dist-info/METADATA
maleo_toolkit_text-0.0.5.dist-info/WHEEL
maleo_toolkit_text-0.0.5.dist-info/top_level.txt
maleo_toolkit_text-0.0.5.dist-info/RECORD
