Metadata-Version: 2.4
Name: maleo-toolkit-text
Version: 0.0.5
Summary: Text toolkit package for MaleoSuite
Author-email: Agra Bima Yuda <agra@nexmedis.com>
License: Proprietary
Requires-Python: >=3.12
Requires-Dist: annotated-types>=0.7.0
Requires-Dist: anyio>=4.10.0
Requires-Dist: black>=25.1.0
Requires-Dist: cachetools>=5.5.2
Requires-Dist: certifi>=2025.8.3
Requires-Dist: cfgv>=3.4.0
Requires-Dist: charset-normalizer>=3.4.3
Requires-Dist: click>=8.2.1
Requires-Dist: distlib>=0.4.0
Requires-Dist: filelock>=3.19.1
Requires-Dist: fsspec>=2025.7.0
Requires-Dist: google-auth>=2.40.3
Requires-Dist: google-genai>=1.32.0
Requires-Dist: h11>=0.16.0
Requires-Dist: hf-xet>=1.1.9
Requires-Dist: httpcore>=1.0.9
Requires-Dist: httpx>=0.28.1
Requires-Dist: huggingface-hub>=0.34.4
Requires-Dist: identify>=2.6.13
Requires-Dist: idna>=3.10
Requires-Dist: jsonpatch>=1.33
Requires-Dist: jsonpointer>=3.0.0
Requires-Dist: langchain-core>=0.3.75
Requires-Dist: langchain-huggingface>=0.3.1
Requires-Dist: langsmith>=0.4.21
Requires-Dist: maleo-types>=0.0.5
Requires-Dist: mypy_extensions>=1.1.0
Requires-Dist: nodeenv>=1.9.1
Requires-Dist: orjson>=3.11.3
Requires-Dist: packaging>=25.0
Requires-Dist: pathspec>=0.12.1
Requires-Dist: platformdirs>=4.4.0
Requires-Dist: pre_commit>=4.3.0
Requires-Dist: pyasn1>=0.6.1
Requires-Dist: pyasn1_modules>=0.4.2
Requires-Dist: pydantic>=2.11.7
Requires-Dist: pydantic_core>=2.33.2
Requires-Dist: PyYAML>=6.0.2
Requires-Dist: requests>=2.32.5
Requires-Dist: requests-toolbelt>=1.0.0
Requires-Dist: rsa>=4.9.1
Requires-Dist: sniffio>=1.3.1
Requires-Dist: tenacity>=9.1.2
Requires-Dist: tokenizers>=0.22.0
Requires-Dist: tqdm>=4.67.1
Requires-Dist: typing-inspection>=0.4.1
Requires-Dist: typing_extensions>=4.15.0
Requires-Dist: urllib3>=2.5.0
Requires-Dist: virtualenv>=20.34.0
Requires-Dist: websockets>=15.0.1
Requires-Dist: zstandard>=0.24.0
